[
    {
        "pub_date": "30-01-2025",
        "title": "Linux Operations Engineer",
        "company": "Netcompany A/S",
        "location": "København, Aarhus eller Aalborg",
        "job_URL": "https://smrtr.io/nkDkK"
    },
    {
        "pub_date": "30-01-2025",
        "title": "Dynamics 365 Manager – driv F&O og Sales i en global virksomhed",
        "company": "Geveko Markings Denmark A/S",
        "location": "Rudkøbing eller Kastrup",
        "job_URL": "https://candidate.hr-manager.net/ApplicationInit.aspx?cid=2395&ProjectId=143658&DepartmentId=18958&MediaId=5&SkipAdvertisement=False"
    },
    {
        "pub_date": "29-01-2025",
        "title": "Afdelingsleder til IT-drift & Support",
        "company": "Nordværk I/S",
        "location": "Aalborg Øst",
        "job_URL": "https://candidate.hr-manager.net/ApplicationInit.aspx?cid=2768&ProjectId=143716&DepartmentId=18973&MediaId=4629"
    },
    {
        "pub_date": "29-01-2025",
        "title": "Head of IT & Business Systems",
        "company": "Continia Software A/S",
        "location": "Copenhagen or Nørresundby",
        "job_URL": "https://candidate.hr-manager.net/ApplicationInit.aspx?cid=2032&ProjectId=143674&DepartmentId=18974&MediaId=5"
    },
    {
        "pub_date": "27-01-2025",
        "title": "IT-kyndig fagansvarlig til Vejdirektoratets vintertjeneste",
        "company": "Vejdirektoratet",
        "location": "Aalborg Øst",
        "job_URL": "https://candidate.hr-manager.net/ApplicationInit.aspx?cid=5001&ProjectId=186112&DepartmentId=10289&MediaId=5"
    },
    {
        "pub_date": "24-01-2025",
        "title": "5G DevOps Testing and Integration Engineer",
        "company": "Rohde & Schwarz Technology Center A/S",
        "location": "Aalborg",
        "job_URL": "https://www.jobindex.dk/jobannonce/h1516801/5g-devops-testing-and-integration-engineer"
    },
    {
        "pub_date": "23-01-2025",
        "title": "IT-driftsmedarbejder",
        "company": "IT Center Nord",
        "location": "Aalborg",
        "job_URL": "https://www.innomate.com/InnomatePublicPagesMedarb/JobNotice.aspx?CompanyId=tcaa&JobNoticeId=1036"
    },
    {
        "pub_date": "20-01-2025",
        "title": "IT-Supporter",
        "company": "Sjørring Maskinfabrik A/S",
        "location": "Thisted",
        "job_URL": "https://www.sjorring.com/career?hr=show-job%2F234479%26locale%3Den_US"
    },
    {
        "pub_date": "17-01-2025",
        "title": "Senior Compliance Manager",
        "company": "Continia Software A/S",
        "location": "Copenhagen or Nørresundby",
        "job_URL": "https://candidate.hr-manager.net/ApplicationInit.aspx?cid=2032&ProjectId=143671&DepartmentId=18974&MediaId=5"
    },
    {
        "pub_date": "17-01-2025",
        "title": "Business Central Support Engineer - Document Capture Support Team",
        "company": "Continia Software A/S",
        "location": "Copenhagen or Nørresundby",
        "job_URL": "https://candidate.hr-manager.net/ApplicationInit.aspx?cid=2032&ProjectId=143670&DepartmentId=18974&MediaId=5"
    },
    {
        "pub_date": "16-01-2025",
        "title": "Dygtig og praktisk orienteret System Ingeniør",
        "company": "Aalborg Portland",
        "location": "Aalborg Øst",
        "job_URL": "https://www.aalborgportland.dk/karriere/job/vis-job/3452689/130141/jobindex&iso=dk/"
    },
    {
        "pub_date": "13-01-2025",
        "title": "IT-systemadministrator",
        "company": "CS WIND Offshore A/S",
        "location": "Aalborg Ø",
        "job_URL": "https://www.cswoffshore.com/join-us/job-openings/vacancy?id=13-01-2025&culture=da-DK"
    },
    {
        "pub_date": "13-01-2025",
        "title": "Solution Architect – sæt dit præg på Netics infrastruktur",
        "company": "Netic A/S",
        "location": "Aalborg eller Aarhus N",
        "job_URL": "https://www.netic.dk/ledige-stillinger/?hr=show-job%2F185665%26locale%3Dda_DK"
    },
    {
        "pub_date": "13-01-2025",
        "title": "IT- og Digitaliseringschef",
        "company": "Curia",
        "location": "Aalborg Ø",
        "job_URL": "https://www.curia.dk/ledige-stillinger?jobid=22281&locale=da_DK"
    },
    {
        "pub_date": "06-02-2025",
        "title": "IT-medarbejder til understøttelse af slutbrugerudstyr hos Digitalisering og IT i Region Nordjylland",
        "company": "Region Nordjylland",
        "location": "Aalborg",
        "job_URL": "https://www.jobindex.dk/jobannonce/r12999689/it-medarbejder-til-understoettelse-af-slutbrugerudstyr-hos-digitalisering-og-it-i-region-nordjylland"
    },
    {
        "pub_date": "05-02-2025",
        "title": "Lead System Architect",
        "company": "RTX A/S",
        "location": "Nørresundby",
        "job_URL": "https://rtx.easycruit.com/vacancy/3439477/164407?iso=us"
    },
    {
        "pub_date": "04-02-2025",
        "title": "IT Supporter",
        "company": "DSI Dantech",
        "location": "Aalborg",
        "job_URL": "https://dsidantech.com/career?hr=show-job%2F238546%26locale%3Dda_DK"
    },
    {
        "pub_date": "04-02-2025",
        "title": "Serviceminded IT-supporter til vores kontor i Hjørring",
        "company": "Altiden",
        "location": "Hjørring",
        "job_URL": "https://jobs.altiden.dk/jobs/5501921-altiden-soger-serviceminded-it-supporter-til-vores-kontor-i-hjorring"
    },
    {
        "pub_date": "03-02-2025",
        "title": "Barselsvikariat: Vil du være med til at uddanne fremtidens IT-supportere og datateknikere?",
        "company": "TECHCOLLEGE",
        "location": "Aalborg Øst",
        "job_URL": "https://www.innomate.com/InnomatePublicPagesMedarb/JobNotice.aspx?CompanyId=tcaa&JobNoticeId=1038"
    }
]