[
    {
        "pub_date": "08-05-2024",
        "title": "Digital marketingspecialist og webmaster",
        "company": "Miljømærkning Danmark",
        "location": "København eller Løgstør",
        "job_URL": "https://ecolabel.career.emply.com/ad/digital-marketingspecialist-og-webmaster/2nlqmq/da"
    },
    {
        "pub_date": "07-05-2024",
        "title": "Marketing Koordinator Lyngsoe Systems Library Solutions",
        "company": "Hviid & Larsen ApS",
        "location": "Aars",
        "job_URL": "https://www.hviidoglarsen.dk/jobs?hr=show-job/198000&linkref=199163&locale=da_DK"
    }
]