[
    {
        "pub_date": "09-09-2024",
        "title": "User Experience Designer (barselsvikariat)",
        "company": "Telenor",
        "location": "Aalborg og København SV",
        "job_URL": "https://candidate.hr-manager.net/ApplicationInit.aspx?cid=1311&ProjectId=145834&DepartmentId=18957&MediaId=5"
    },
    {
        "pub_date": "05-09-2024",
        "title": "Innovativ E-commerce ekspert",
        "company": "Aktieselskabet Glerups.DK",
        "location": "Aars",
        "job_URL": "https://www.jobindex.dk/jobannonce/h1498251/innovativ-e-commerce-ekspert"
    },
    {
        "pub_date": "02-09-2024",
        "title": "Selvkørende og højtragende tekniker",
        "company": "Temp-Team A/S",
        "location": "Allingåbro",
        "job_URL": "https://temp-team.dk/job-search/selvkorende-og-hojtragende-tekniker-soges-394336"
    }
]