[
    {
        "pub_date": "25-09-2024",
        "title": "Varemodtager",
        "company": "Bygma",
        "location": "Hjørring",
        "job_URL": "https://jobs.bygma.dk/job/Hj%C3%B8rring-Varemodtager-til-Bygma-Hj%C3%B8rring-9800/992204955/"
    },
    {
        "pub_date": "25-09-2024",
        "title": "Lagermedarbejder",
        "company": "Pajo-Bolte A/S",
        "location": "Hobro",
        "job_URL": "https://www.metal-supply.dk/job/view/696709/lagermedarbejder"
    },
    {
        "pub_date": "24-09-2024",
        "title": "Specialarbejder med teknisk flair søges til AAU Energi – Aalborg Universitet",
        "company": "Aalborg Universitet",
        "location": "Aalborg",
        "job_URL": "https://www.vacancies.aau.dk/technical-and-administrative-positions/show-vacancy/vacancyId/1219238"
    },
    {
        "pub_date": "20-09-2024",
        "title": "Erfaren og energisk teamleder til lager",
        "company": "Luksusbaby A/S",
        "location": "Støvring",
        "job_URL": "https://candidate.hr-manager.net/ApplicationInit.aspx?cid=2758&ProjectId=143609&DepartmentId=18959&MediaId=5&SkipAdvertisement=False"
    },
    {
        "pub_date": "11-10-2024",
        "title": "Lager- og kundeservicemedarbejder til værktøj og værktøjsmaskiner",
        "company": "GLOBALTOOLS ApS",
        "location": "Støvring",
        "job_URL": "https://www.nordjyskejob.dk/resultat/lager-og-kundeservicemedarbejder-til-vaerktoej-og-vaerktoejsmaskiner-lja-85743146.aspx?jobId=LJA-85743146&list=SearchResultsJobsIds&index=9&querydesc=SearchJobQueryDescription&viewedfrom=1"
    },
    {
        "pub_date": "09-10-2024",
        "title": "Energisk medarbejder til frysehus i Hirtshals",
        "company": "Lineage",
        "location": "Hirtshals",
        "job_URL": "https://mit.moment.dk/jobopslag/vis?no=192767"
    },
    {
        "pub_date": "07-10-2024",
        "title": "Lagerindkøber/Reservedelsekspedient søges til vores afdeling i Hjørring",
        "company": "Nordjysk Lift ApS",
        "location": "Hjørring",
        "job_URL": "https://www.jobindex.dk/jobannonce/r12776319/lagerindkoeber-reservedelsekspedient-soeges-til-vores-afdeling-i-hjoerring"
    },
    {
        "pub_date": "07-10-2024",
        "title": "Pajo-Bolte søger en målrettet og engageret lagerchef",
        "company": "Pajo-Bolte A/S",
        "location": "Hobro",
        "job_URL": "https://www.metal-supply.dk/job/view/699158/pajobolte_soger_en_malrettet_og_engageret_lagerchef"
    },
    {
        "pub_date": "03-10-2024",
        "title": "NOWAS A/S søger en lagermedarbejder",
        "company": "",
        "location": "Løgstør",
        "job_URL": "https://www.jobindex.dk/jobannonce/r12768375/nowas-a-s-soeger-en-lagermedarbejder"
    },
    {
        "pub_date": "02-10-2024",
        "title": "Frysehusmedarbejder m/k",
        "company": "Lineage",
        "location": "Hirtshals, Skagen",
        "job_URL": "https://www.jobindex.dk/jobannonce/h1504082/frysehusmedarbejder-m-k"
    },
    {
        "pub_date": "01-10-2024",
        "title": "Lagersouschef",
        "company": "Dragsbæk A/S",
        "location": "Thisted",
        "job_URL": "https://dragsbaek.dk/job.aspx?hr=show-job/218894&linkref=234617&locale=da_DK"
    },
    {
        "pub_date": "01-10-2024",
        "title": "Afdelingsleder, Aalborg Distributionscenter",
        "company": "Coop Logistik",
        "location": "Aalborg SV",
        "job_URL": "https://jobs.coop.dk/job/Afdelingsleder%2C-Aalborg-Distributionscenter/804285002/"
    },
    {
        "pub_date": "01-10-2024",
        "title": "Lagerkoordinator",
        "company": "MatchMind",
        "location": "Brønderslev",
        "job_URL": "https://matchmind.dk/ledige-jobs?hr=show-job/218637&linkref=234213&locale=da_DK"
    }
]